pybuilder_docker/__init__.py
pybuilder_docker-0.1.15.dist-info/METADATA
pybuilder_docker-0.1.15.dist-info/WHEEL
pybuilder_docker-0.1.15.dist-info/namespace_packages.txt
pybuilder_docker-0.1.15.dist-info/top_level.txt
pybuilder_docker-0.1.15.dist-info/zip-safe
pybuilder_docker-0.1.15.dist-info/RECORD
