Metadata-Version: 2.1
Name: pybuilder-docker
Version: 0.1.15
Summary: A pybuilder plugin that stages a python package into a docker container and optionally publishes it to a registry.
Home-page: https://github.com/AlienVault-Engineering/pybuilder-docker
Author: 
Author-email: 
Maintainer: 
Maintainer-email: 
License: Apache 2.0
Platform: UNKNOWN
Classifier: Development Status :: 3 - Alpha
Classifier: Programming Language :: Python
